temagics/__init__.py
temagics/comm_handlers.py
temagics/magics.py
temagics-1.0.9.dist-info/DESCRIPTION.rst
temagics-1.0.9.dist-info/METADATA
temagics-1.0.9.dist-info/RECORD
temagics-1.0.9.dist-info/WHEEL
temagics-1.0.9.dist-info/metadata.json
temagics-1.0.9.dist-info/top_level.txt
