Metadata-Version: 2.0
Name: temagics
Version: 1.0.9
Summary: Tellurium IPython cell magics
Home-page: https://github.com/0u812/temagics
Author: J. Kyle Medley
Author-email: UNKNOWN
License: UNKNOWN
Platform: UNKNOWN
